pyfmgng/__about__.py
pyfmgng/__init__.py
pyfmgng/adom.py
pyfmgng/client.py
pyfmgng/dataclasses.py
pyfmgng/firewall.py
pyfmgng/fmgapi.py
pyfmgng/fmgsystem.py
pyfmgng/vdom.py
pyfmgng-0.0.1.dist-info/METADATA
pyfmgng-0.0.1.dist-info/WHEEL
pyfmgng-0.0.1.dist-info/licenses/LICENSE
pyfmgng-0.0.1.dist-info/RECORD
