Metadata-Version: 2.1
Name: pyfmgng
Version: 0.0.1
Summary: FortiManager SDK NG
Project-URL: Homepage, https://github.com/pertoft/pyfmg-ng
Project-URL: Bug Tracker, https://github.com/pertoft/pyfmg-ng/issues
Author-email: Per Abildgaard Toft <p@t1.dk>
License-File: LICENSE
Classifier: License :: OSI Approved :: MIT License
Classifier: Operating System :: OS Independent
Classifier: Programming Language :: Python :: 3
Requires-Python: >=3.8
